robologs/__initi__.py
robologs-0.0.1a0.dist-info/entry_points.txt
robologs-0.0.1a0.dist-info/WHEEL
robologs-0.0.1a0.dist-info/METADATA
robologs-0.0.1a0.dist-info/RECORD
